[
  {
    "Container": "format_ChangeDefaultToBlank",
    "RuleGUID": "53b4c071-7ba8-433d-9259-67e61f612e2e",
    "RuleName": "Is Field = 00000000",
    "RuleID": "",
    "FunctionName": "HasRegExpr",
    "ParentGUID": null,
    "ParentActionIndex": null,
    "Children": [],
    "Actions": [
      {
        "ActionValue": "4",
        "ActionName": "All",
        "ChildRules": [
          {
            "Container": "format_ChangeDefaultToBlank",
            "RuleGUID": "6416bb58-992d-4080-9007-8856706f3d24",
            "RuleName": "DeleteLines",
            "RuleID": "",
            "FunctionName": "DeleteLines",
            "ParentGUID": "53b4c071-7ba8-433d-9259-67e61f612e2e",
            "ParentActionIndex": 0,
            "Children": [],
            "Actions": [
              {
                "ActionValue": "0",
                "ActionName": "",
                "ChildRules": [],
                "Attributes": {}
              },
              {
                "ActionValue": "0",
                "ActionName": "",
                "ChildRules": [],
                "Attributes": {}
              },
              {
                "ActionValue": "0",
                "ActionName": "",
                "ChildRules": [],
                "Attributes": {}
              }
            ],
            "Attributes": {
              "_ParamList0": "{0}",
              "_FunctionVersion": "1",
              "DeleteBlanks": "0",
              "MinLinesBeforeDelete": "0",
              "LinesFrom": "0"
            }
          }
        ],
        "Attributes": {}
      },
      {
        "ActionValue": "0",
        "ActionName": "",
        "ChildRules": [],
        "Attributes": {}
      },
      {
        "ActionValue": "0",
        "ActionName": "",
        "ChildRules": [],
        "Attributes": {}
      }
    ],
    "Attributes": {
      "_Description": "\"If so this is a default date from EDIPickup\"",
      "CaseSensitive": "1",
      "_ParamList0": "{0}",
      "RegularExpression": "\"^00000000$\"",
      "_FunctionVersion": "65539"
    }
  },
  {
    "Container": "format_ChangeDefaultToBlank",
    "RuleGUID": "fb4a834d-a42b-4039-815e-13e0b17d6c95",
    "RuleName": "Is Field = 0",
    "RuleID": "",
    "FunctionName": "HasRegExpr",
    "ParentGUID": null,
    "ParentActionIndex": null,
    "Children": [],
    "Actions": [
      {
        "ActionValue": "4",
        "ActionName": "All",
        "ChildRules": [
          {
            "Container": "format_ChangeDefaultToBlank",
            "RuleGUID": "9824b258-da0e-4809-a5b1-caa1b5eda224",
            "RuleName": "DeleteLines",
            "RuleID": "",
            "FunctionName": "DeleteLines",
            "ParentGUID": "fb4a834d-a42b-4039-815e-13e0b17d6c95",
            "ParentActionIndex": 0,
            "Children": [],
            "Actions": [
              {
                "ActionValue": "0",
                "ActionName": "",
                "ChildRules": [],
                "Attributes": {}
              },
              {
                "ActionValue": "0",
                "ActionName": "",
                "ChildRules": [],
                "Attributes": {}
              },
              {
                "ActionValue": "0",
                "ActionName": "",
                "ChildRules": [],
                "Attributes": {}
              }
            ],
            "Attributes": {
              "_ParamList0": "{0}",
              "_FunctionVersion": "1",
              "DeleteBlanks": "0",
              "MinLinesBeforeDelete": "0",
              "LinesFrom": "0"
            }
          }
        ],
        "Attributes": {}
      },
      {
        "ActionValue": "0",
        "ActionName": "",
        "ChildRules": [],
        "Attributes": {}
      },
      {
        "ActionValue": "0",
        "ActionName": "",
        "ChildRules": [],
        "Attributes": {}
      }
    ],
    "Attributes": {
      "_Description": "\"If so this is a default date from EDIPickup\"",
      "CaseSensitive": "1",
      "_ParamList0": "{0}",
      "RegularExpression": "\"^0$\"",
      "_FunctionVersion": "65539"
    }
  },
  {
    "Container": "format_ChangeDefaultToBlank",
    "RuleGUID": "d95bfb49-fe98-4f4d-937a-562eda2c939a",
    "RuleName": "Is Field = 00",
    "RuleID": "",
    "FunctionName": "HasRegExpr",
    "ParentGUID": null,
    "ParentActionIndex": null,
    "Children": [],
    "Actions": [
      {
        "ActionValue": "4",
        "ActionName": "All",
        "ChildRules": [
          {
            "Container": "format_ChangeDefaultToBlank",
            "RuleGUID": "7fa9b96d-97a8-41bc-a538-33f860bf4701",
            "RuleName": "DeleteLines",
            "RuleID": "",
            "FunctionName": "DeleteLines",
            "ParentGUID": "d95bfb49-fe98-4f4d-937a-562eda2c939a",
            "ParentActionIndex": 0,
            "Children": [],
            "Actions": [
              {
                "ActionValue": "0",
                "ActionName": "",
                "ChildRules": [],
                "Attributes": {}
              },
              {
                "ActionValue": "0",
                "ActionName": "",
                "ChildRules": [],
                "Attributes": {}
              },
              {
                "ActionValue": "0",
                "ActionName": "",
                "ChildRules": [],
                "Attributes": {}
              }
            ],
            "Attributes": {
              "_ParamList0": "{0}",
              "_FunctionVersion": "1",
              "DeleteBlanks": "0",
              "MinLinesBeforeDelete": "0",
              "LinesFrom": "0"
            }
          }
        ],
        "Attributes": {}
      },
      {
        "ActionValue": "0",
        "ActionName": "",
        "ChildRules": [],
        "Attributes": {}
      },
      {
        "ActionValue": "0",
        "ActionName": "",
        "ChildRules": [],
        "Attributes": {}
      }
    ],
    "Attributes": {
      "_Description": "\"If so this is a default date from EDIPickup\"",
      "CaseSensitive": "1",
      "_ParamList0": "{0}",
      "RegularExpression": "\"^00$\"",
      "_FunctionVersion": "65539"
    }
  },
  {
    "Container": "format_ChangeDefaultToBlank",
    "RuleGUID": "71e946f1-d9e8-42a8-a346-71d7386e319a",
    "RuleName": "Is Field = 00000",
    "RuleID": "",
    "FunctionName": "HasRegExpr",
    "ParentGUID": null,
    "ParentActionIndex": null,
    "Children": [],
    "Actions": [
      {
        "ActionValue": "4",
        "ActionName": "All",
        "ChildRules": [
          {
            "Container": "format_ChangeDefaultToBlank",
            "RuleGUID": "bcd765ba-d0b3-4304-82bf-9c2e6b37a15a",
            "RuleName": "DeleteLines",
            "RuleID": "",
            "FunctionName": "DeleteLines",
            "ParentGUID": "71e946f1-d9e8-42a8-a346-71d7386e319a",
            "ParentActionIndex": 0,
            "Children": [],
            "Actions": [
              {
                "ActionValue": "0",
                "ActionName": "",
                "ChildRules": [],
                "Attributes": {}
              },
              {
                "ActionValue": "0",
                "ActionName": "",
                "ChildRules": [],
                "Attributes": {}
              },
              {
                "ActionValue": "0",
                "ActionName": "",
                "ChildRules": [],
                "Attributes": {}
              }
            ],
            "Attributes": {
              "_ParamList0": "{0}",
              "_FunctionVersion": "1",
              "DeleteBlanks": "0",
              "MinLinesBeforeDelete": "0",
              "LinesFrom": "0"
            }
          }
        ],
        "Attributes": {}
      },
      {
        "ActionValue": "0",
        "ActionName": "",
        "ChildRules": [],
        "Attributes": {}
      },
      {
        "ActionValue": "0",
        "ActionName": "",
        "ChildRules": [],
        "Attributes": {}
      }
    ],
    "Attributes": {
      "_Description": "\"If so this is a default date from EDIPickup\"",
      "CaseSensitive": "1",
      "_ParamList0": "{0}",
      "RegularExpression": "\"^00000$\"",
      "_FunctionVersion": "65539"
    }
  }
]