[
  {
    "Container": "helper_id_mixed_population",
    "RuleGUID": "833efa27-01c0-4721-8daf-f408e7b80574",
    "RuleName": "MixedClaimFlag already M?",
    "RuleID": "",
    "FunctionName": "HasRegExpr",
    "ParentGUID": null,
    "ParentActionIndex": null,
    "Children": [],
    "Actions": [
      {
        "ActionValue": "0",
        "ActionName": "None",
        "ChildRules": [
          {
            "Container": "helper_id_mixed_population",
            "RuleGUID": "36dac09d-7a7e-4d84-b9d6-2a7eabc9d136",
            "RuleName": "Is Field empty?",
            "RuleID": "",
            "FunctionName": "IsEmpty",
            "ParentGUID": "833efa27-01c0-4721-8daf-f408e7b80574",
            "ParentActionIndex": 0,
            "Children": [],
            "Actions": [
              {
                "ActionValue": "4",
                "ActionName": "Yes",
                "ChildRules": [
                  {
                    "Container": "helper_id_mixed_population",
                    "RuleGUID": "fb1590d2-b17c-487f-b37e-55659b313045",
                    "RuleName": "Is MixedClaimFlag already E?",
                    "RuleID": "",
                    "FunctionName": "HasRegExpr",
                    "ParentGUID": "36dac09d-7a7e-4d84-b9d6-2a7eabc9d136",
                    "ParentActionIndex": 0,
                    "Children": [],
                    "Actions": [
                      {
                        "ActionValue": "0",
                        "ActionName": "No",
                        "ChildRules": [
                          {
                            "Container": "helper_id_mixed_population",
                            "RuleGUID": "004e1933-5dd5-4cc4-add9-58773b6b0f93",
                            "RuleName": "Is it P?",
                            "RuleID": "",
                            "FunctionName": "HasRegExpr",
                            "ParentGUID": "fb1590d2-b17c-487f-b37e-55659b313045",
                            "ParentActionIndex": 0,
                            "Children": [],
                            "Actions": [
                              {
                                "ActionValue": "4",
                                "ActionName": "Yes",
                                "ChildRules": [
                                  {
                                    "Container": "helper_id_mixed_population",
                                    "RuleGUID": "d91a24d5-50cc-475c-b58a-ac3982d0b314",
                                    "RuleName": "Set to M",
                                    "RuleID": "",
                                    "FunctionName": "Formatf",
                                    "ParentGUID": "004e1933-5dd5-4cc4-add9-58773b6b0f93",
                                    "ParentActionIndex": 0,
                                    "Children": [],
                                    "Actions": [
                                      {
                                        "ActionValue": "0",
                                        "ActionName": "",
                                        "ChildRules": [],
                                        "Attributes": {}
                                      },
                                      {
                                        "ActionValue": "0",
                                        "ActionName": "",
                                        "ChildRules": [],
                                        "Attributes": {}
                                      }
                                    ],
                                    "Attributes": {
                                      "_ParamList0": "{1}",
                                      "_FunctionVersion": "100",
                                      "_Description": "\"For 'Mixed'\"",
                                      "OutputFormat": "\"M\""
                                    }
                                  }
                                ],
                                "Attributes": {}
                              },
                              {
                                "ActionValue": "0",
                                "ActionName": "No",
                                "ChildRules": [
                                  {
                                    "Container": "helper_id_mixed_population",
                                    "RuleGUID": "e6c936ae-900a-4712-b582-351c6c10c2ed",
                                    "RuleName": "Set to E",
                                    "RuleID": "",
                                    "FunctionName": "Formatf",
                                    "ParentGUID": "004e1933-5dd5-4cc4-add9-58773b6b0f93",
                                    "ParentActionIndex": 1,
                                    "Children": [],
                                    "Actions": [
                                      {
                                        "ActionValue": "0",
                                        "ActionName": "",
                                        "ChildRules": [],
                                        "Attributes": {}
                                      },
                                      {
                                        "ActionValue": "0",
                                        "ActionName": "",
                                        "ChildRules": [],
                                        "Attributes": {}
                                      }
                                    ],
                                    "Attributes": {
                                      "_ParamList0": "{1}",
                                      "_FunctionVersion": "100",
                                      "OutputFormat": "\"E\""
                                    }
                                  }
                                ],
                                "Attributes": {}
                              },
                              {
                                "ActionValue": "260",
                                "ActionName": "",
                                "ChildRules": [],
                                "Attributes": {}
                              }
                            ],
                            "Attributes": {
                              "CaseSensitive": "1",
                              "_ParamList0": "{1}",
                              "RegularExpression": "\"^P$\"",
                              "_FunctionVersion": "65539",
                              "_Description": "\"For 'Populated'\""
                            }
                          }
                        ],
                        "Attributes": {}
                      },
                      {
                        "ActionValue": "0",
                        "ActionName": "",
                        "ChildRules": [],
                        "Attributes": {}
                      },
                      {
                        "ActionValue": "4",
                        "ActionName": "",
                        "ChildRules": [],
                        "Attributes": {}
                      }
                    ],
                    "Attributes": {
                      "CaseSensitive": "1",
                      "_ParamList0": "{1}",
                      "RegularExpression": "\"^E$\"",
                      "_FunctionVersion": "65539",
                      "_Description": "\"For 'Empty'\""
                    }
                  }
                ],
                "Attributes": {}
              },
              {
                "ActionValue": "0",
                "ActionName": "No",
                "ChildRules": [
                  {
                    "Container": "helper_id_mixed_population",
                    "RuleGUID": "d58d35ed-c8f9-4260-a242-cee382ad1e4a",
                    "RuleName": "Is MixedClaimFlag already P?",
                    "RuleID": "",
                    "FunctionName": "HasRegExpr",
                    "ParentGUID": "36dac09d-7a7e-4d84-b9d6-2a7eabc9d136",
                    "ParentActionIndex": 1,
                    "Children": [],
                    "Actions": [
                      {
                        "ActionValue": "0",
                        "ActionName": "No",
                        "ChildRules": [
                          {
                            "Container": "helper_id_mixed_population",
                            "RuleGUID": "3b298f6b-e8ee-45da-8ba3-b6bc2652f5a4",
                            "RuleName": "Is it E?",
                            "RuleID": "",
                            "FunctionName": "HasRegExpr",
                            "ParentGUID": "d58d35ed-c8f9-4260-a242-cee382ad1e4a",
                            "ParentActionIndex": 0,
                            "Children": [],
                            "Actions": [
                              {
                                "ActionValue": "4",
                                "ActionName": "Yes",
                                "ChildRules": [
                                  {
                                    "Container": "helper_id_mixed_population",
                                    "RuleGUID": "8d41a2f4-6eba-44ab-a206-a7880c004d3e",
                                    "RuleName": "Set to M",
                                    "RuleID": "",
                                    "FunctionName": "Formatf",
                                    "ParentGUID": "3b298f6b-e8ee-45da-8ba3-b6bc2652f5a4",
                                    "ParentActionIndex": 0,
                                    "Children": [],
                                    "Actions": [
                                      {
                                        "ActionValue": "0",
                                        "ActionName": "",
                                        "ChildRules": [],
                                        "Attributes": {}
                                      },
                                      {
                                        "ActionValue": "0",
                                        "ActionName": "",
                                        "ChildRules": [],
                                        "Attributes": {}
                                      }
                                    ],
                                    "Attributes": {
                                      "_ParamList0": "{1}",
                                      "_FunctionVersion": "100",
                                      "_Description": "\"For 'Mixed'\"",
                                      "OutputFormat": "\"M\""
                                    }
                                  }
                                ],
                                "Attributes": {}
                              },
                              {
                                "ActionValue": "0",
                                "ActionName": "No",
                                "ChildRules": [
                                  {
                                    "Container": "helper_id_mixed_population",
                                    "RuleGUID": "bd569eae-2237-4f7a-aad4-32843e8c5e75",
                                    "RuleName": "Set to P",
                                    "RuleID": "",
                                    "FunctionName": "Formatf",
                                    "ParentGUID": "3b298f6b-e8ee-45da-8ba3-b6bc2652f5a4",
                                    "ParentActionIndex": 1,
                                    "Children": [],
                                    "Actions": [
                                      {
                                        "ActionValue": "0",
                                        "ActionName": "",
                                        "ChildRules": [],
                                        "Attributes": {}
                                      },
                                      {
                                        "ActionValue": "0",
                                        "ActionName": "",
                                        "ChildRules": [],
                                        "Attributes": {}
                                      }
                                    ],
                                    "Attributes": {
                                      "_ParamList0": "{1}",
                                      "_FunctionVersion": "100",
                                      "OutputFormat": "\"P\""
                                    }
                                  }
                                ],
                                "Attributes": {}
                              },
                              {
                                "ActionValue": "260",
                                "ActionName": "",
                                "ChildRules": [],
                                "Attributes": {}
                              }
                            ],
                            "Attributes": {
                              "CaseSensitive": "1",
                              "_ParamList0": "{1}",
                              "RegularExpression": "\"^E$\"",
                              "_FunctionVersion": "65539",
                              "_Description": "\"For 'Empty'\""
                            }
                          }
                        ],
                        "Attributes": {}
                      },
                      {
                        "ActionValue": "0",
                        "ActionName": "",
                        "ChildRules": [],
                        "Attributes": {}
                      },
                      {
                        "ActionValue": "4",
                        "ActionName": "",
                        "ChildRules": [],
                        "Attributes": {}
                      }
                    ],
                    "Attributes": {
                      "CaseSensitive": "1",
                      "_ParamList0": "{1}",
                      "RegularExpression": "\"^P$\"",
                      "_FunctionVersion": "65539",
                      "_Description": "\"For 'Populated'\""
                    }
                  }
                ],
                "Attributes": {}
              },
              {
                "ActionValue": "260",
                "ActionName": "",
                "ChildRules": [],
                "Attributes": {}
              }
            ],
            "Attributes": {
              "_ParamList0": "{0}",
              "_FunctionVersion": "3"
            }
          }
        ],
        "Attributes": {}
      },
      {
        "ActionValue": "0",
        "ActionName": "",
        "ChildRules": [],
        "Attributes": {}
      },
      {
        "ActionValue": "4",
        "ActionName": "",
        "ChildRules": [],
        "Attributes": {}
      }
    ],
    "Attributes": {
      "CaseSensitive": "1",
      "_ParamList0": "{1}",
      "RegularExpression": "\"^M$\"",
      "_FunctionVersion": "65539"
    }
  }
]