[
  {
    "Container": "output_SplitFetchCTSRecords",
    "RuleGUID": "5de25c3d-d718-460c-b6d0-8cf6aae44e12",
    "RuleName": "Fetch all Coverage Rows",
    "RuleID": "",
    "FunctionName": "SelectSelectedListTableApproxMatch",
    "ParentGUID": null,
    "ParentActionIndex": null,
    "Children": [],
    "Actions": [
      {
        "ActionValue": "0",
        "ActionName": "",
        "ChildRules": [],
        "Attributes": {}
      },
      {
        "ActionValue": "0",
        "ActionName": "",
        "ChildRules": [],
        "Attributes": {}
      },
      {
        "ActionValue": "0",
        "ActionName": "",
        "ChildRules": [],
        "Attributes": {}
      },
      {
        "ActionValue": "0",
        "ActionName": "",
        "ChildRules": [],
        "Attributes": {}
      },
      {
        "ActionValue": "0",
        "ActionName": "",
        "ChildRules": [],
        "Attributes": {}
      },
      {
        "ActionValue": "0",
        "ActionName": "",
        "ChildRules": [],
        "Attributes": {}
      },
      {
        "ActionValue": "0",
        "ActionName": "",
        "ChildRules": [],
        "Attributes": {}
      },
      {
        "ActionValue": "0",
        "ActionName": "",
        "ChildRules": [],
        "Attributes": {}
      }
    ],
    "Attributes": {
      "MaxMatchCount": "99999",
      "MaxIndexCount": "0",
      "EmptyKeyFails": "1",
      "AnyEmptyKeysFails": "0",
      "Table": "\"odbc_MemCovInfo\"",
      "SelectionList": "\"selectionlist_MemCTSInfo\"",
      "NextInstance": "0",
      "_ParamList0": "{0}",
      "_ParamList1": "{}",
      "_FunctionVersion": "131076",
      "SelectionListColumns": "{\"MEM_MTV_PID\",\"MEM_COV_UNQ_ID\",\"MEM_COV_CTRCT_ID\",\"MEM_COV_EFF_DT\",\"MEM_COV_END_DT\",\"MEM_COV_GRP\",\"MEM_COV_DVSN\",\"MEM_COV_FIN_MRKT\",\"MEM_COV_CTRCT_TYP_CD\",\"MEM_COV_SOR\"}",
      "DataColumns": "{\"MEM_MTV_PID\",\"MEM_COV_UNQ_ID\",\"MEM_COV_CTRCT_ID\",\"MEM_COV_EFF_DT\",\"MEM_COV_END_DT\",\"MEM_COV_GRP\",\"MEM_COV_DVSN\",\"MEM_COV_FIN_MRKT\",\"MEM_COV_CTRCT_TYP_CD\",\"MEM_COV_SOR\"}",
      "EscapeFields": "{\"0\",\"0\",\"0\",\"0\",\"0\",\"0\",\"0\",\"0\",\"0\",\"0\"}",
      "PlugFields": "{\"0\",\"0\",\"0\",\"0\",\"0\",\"0\",\"0\",\"0\",\"0\",\"0\"}",
      "DataTableDataField": "{-1,-1,-1,-1,-1,-1,-1,-1,-1,-1}",
      "DataTableEmptyField": "{-1,-1,-1,-1,-1,-1,-1,-1,-1,-1}",
      "EmptyTableDataField": "{-1,-1,-1,-1,-1,-1,-1,-1,-1,-1}",
      "ExactColumns": "{\"MEM_MTV_PID\"}",
      "CatchResourceUnavailable": "0"
    }
  },
  {
    "Container": "output_SplitFetchCTSRecords",
    "RuleGUID": "4a4c7d51-7f2c-4308-9186-631418b3050d",
    "RuleName": "Log SL",
    "RuleID": "",
    "FunctionName": "LogSL",
    "ParentGUID": null,
    "ParentActionIndex": null,
    "Children": [],
    "Actions": [
      {
        "ActionValue": "0",
        "ActionName": "",
        "ChildRules": [],
        "Attributes": {}
      }
    ],
    "Attributes": {
      "SelectionList": "\"selectionlist_MemCTSInfo\"",
      "_FunctionVersion": "1",
      "LogLevel": "12"
    }
  }
]