[
  {
    "Container": "helper_MapStrToChckbox_RelCode",
    "RuleGUID": "bc0d2ddf-2e90-4d81-9a27-78f26a92e1bf",
    "RuleName": "Filter leading S",
    "RuleID": "",
    "FunctionName": "FormatRegExpr",
    "ParentGUID": null,
    "ParentActionIndex": null,
    "Children": [],
    "Actions": [
      {
        "ActionValue": "0",
        "ActionName": "",
        "ChildRules": [],
        "Attributes": {}
      },
      {
        "ActionValue": "0",
        "ActionName": "",
        "ChildRules": [],
        "Attributes": {}
      },
      {
        "ActionValue": "0",
        "ActionName": "",
        "ChildRules": [],
        "Attributes": {}
      }
    ],
    "Attributes": {
      "RepeatInLine": "0",
      "RepeatInAllLines": "0",
      "_ParamList0": "{1}",
      "_FunctionVersion": "2",
      "InputFormat": "\"^S\\134(.*\\134)$\"",
      "OutputFormat": "\"\\1341\"",
      "CaseSensitive2": "0",
      "_RegExTestValues": "{\"10\",\"S10\",\"SS10\",\"1S0\"}",
      "_RegExMatchBaseline": "{}",
      "_RegExOutputBaseline": "{}"
    }
  },
  {
    "Container": "helper_MapStrToChckbox_RelCode",
    "RuleGUID": "f27e21f4-5a0c-4937-a7d8-2cebc33e067e",
    "RuleName": "Map letter to relation",
    "RuleID": "",
    "FunctionName": "MapStringToCheckbox",
    "ParentGUID": null,
    "ParentActionIndex": null,
    "Children": [],
    "Actions": [
      {
        "ActionValue": "0",
        "ActionName": "",
        "ChildRules": [],
        "Attributes": {}
      },
      {
        "ActionValue": "0",
        "ActionName": "",
        "ChildRules": [],
        "Attributes": {}
      },
      {
        "ActionValue": "0",
        "ActionName": "",
        "ChildRules": [],
        "Attributes": {}
      }
    ],
    "Attributes": {
      "_ParamList0": "{0}",
      "_FunctionVersion": "1",
      "OMRSubfieldName": "{\"Self\",\"Self\",\"Self\",\"Self\",\"Spouse\",\"Spouse\",\"Spouse\",\"Child\",\"Child\",\"Child\",\"Child\",\"Child\",\"Other\",\"Other\",\"Other\",\"Other\"}",
      "ToStrings": "{\"01\",\"10\",\"11\",\"12\",\"02\",\"20\",\"21\",\"03\",\"30\",\"32\",\"31\",\"33\",\"04\",\"40\",\"##DP\",\"##SS\"}",
      "UncheckedStrings": "{\" \",\"0\"}",
      "_Sources": "{\"OCR_AEG\"}",
      "_ParamListOMRIndex0": "{-1}",
      "_ParamList1": "{1}",
      "_ParamListOMRIndex1": "{-1}"
    }
  }
]